alerk/__init__.py
alerk/args_parsing.py
alerk/key_manager.py
alerk/main.py
alerk/main_shifty.py
alerk/process_responce.py
alerk/setting_manager.py
alerk/smalk.py
alerk/telegram_manager.py
alerk/tests.py
alerk-0.1.1.dist-info/licenses/LICENSE
alerk-0.1.1.dist-info/METADATA
alerk-0.1.1.dist-info/WHEEL
alerk-0.1.1.dist-info/entry_points.txt
alerk-0.1.1.dist-info/top_level.txt
alerk-0.1.1.dist-info/RECORD
