Metadata-Version: 2.4
Name: alerk
Version: 0.1.1
Summary: alerk, if alert, reports on events.
Author-email: The220th <The220th@gmail.com>
License-Expression: MIT
Project-URL: Homepage, https://github.com/The220th/alerk
Project-URL: Issues, https://github.com/The220th/alerk/issues
Classifier: Programming Language :: Python :: 3
Classifier: Operating System :: OS Independent
Requires-Python: >=3.7
License-File: LICENSE
Requires-Dist: alerk_pack
Requires-Dist: argparse
Requires-Dist: ksupk
Requires-Dist: numpy
Requires-Dist: requests
Requires-Dist: pyyaml
Requires-Dist: uvicorn
Requires-Dist: fastapi
Requires-Dist: cryptography
Requires-Dist: pydantic
Requires-Dist: pyTelegramBotAPI
Dynamic: license-file
